brain_games/__init__.py
brain_games/cli.py
brain_games/games/brain_calc_logic.py
brain_games/games/brain_even_logic.py
brain_games/games/brain_gcd_logic.py
brain_games/games/brain_prime_logic.py
brain_games/games/brain_progression_logic.py
brain_games/scripts/.brain_games.py.swo
brain_games/scripts/__init__.py
brain_games/scripts/brain_calc.py
brain_games/scripts/brain_even.py
brain_games/scripts/brain_games.py
brain_games/scripts/brain_gcd.py
brain_games/scripts/brain_prime.py
brain_games/scripts/brain_progression.py
brain_games/scripts/engine.py
siderai_brain_games-1.1.0.dist-info/entry_points.txt
siderai_brain_games-1.1.0.dist-info/WHEEL
siderai_brain_games-1.1.0.dist-info/METADATA
siderai_brain_games-1.1.0.dist-info/RECORD
