Metadata-Version: 2.1
Name: siderai-brain-games
Version: 1.1.0
Summary: Brain Games is a pack of five console arithmetic games
Home-page: https://github.com/siderai/brain-games
Author: Alexander Sidorov
Author-email: sidai@bk.ru
Requires-Python: >=3.8,<4.0
Classifier: Programming Language :: Python :: 3
Classifier: Programming Language :: Python :: 3.10
Classifier: Programming Language :: Python :: 3.8
Classifier: Programming Language :: Python :: 3.9
Classifier: Topic :: Games/Entertainment :: Puzzle Games
Requires-Dist: prompt (>=0.4.1,<0.5.0)
Project-URL: Repository, https://github.com/siderai/brain-games
